app_adapter.py
bootstrap.py
container_control_core.py
container_control/__init__.py
container_control/scaffold.py
container_control/templates/Dockerfile.example
container_control/templates/__init__.py
container_control/templates/config.yaml.example
container_control-1.1.0.dist-info/licenses/LICENSE
container_control-1.1.0.dist-info/METADATA
container_control-1.1.0.dist-info/WHEEL
container_control-1.1.0.dist-info/entry_points.txt
container_control-1.1.0.dist-info/top_level.txt
container_control-1.1.0.dist-info/RECORD
