Metadata-Version: 2.4
Name: container-control
Version: 1.1.0
Summary: Container Control Core for Showrunner
Author: Showrunner Team
License-Expression: LicenseRef-Proprietary
Project-URL: Documentation, https://github.com/rdwr-taly/container-control#readme
Project-URL: Repository, https://github.com/rdwr-taly/container-control
Project-URL: Issues, https://github.com/rdwr-taly/container-control/issues
Project-URL: Changelog, https://github.com/rdwr-taly/container-control/blob/main/CHANGELOG.md
Keywords: containers,fastapi,scaffolding,showrunner
Classifier: Programming Language :: Python :: 3
Classifier: Programming Language :: Python :: 3.10
Classifier: Framework :: FastAPI
Classifier: Operating System :: POSIX :: Linux
Classifier: Topic :: System :: Systems Administration
Requires-Python: >=3.10
License-File: LICENSE
Requires-Dist: fastapi>=0.95
Requires-Dist: uvicorn>=0.20
Requires-Dist: psutil>=5.9
Requires-Dist: ruamel.yaml>=0.17
Requires-Dist: pydantic>=1.10
Provides-Extra: test
Requires-Dist: pytest>=7; extra == "test"
Requires-Dist: httpx>=0.24; extra == "test"
Dynamic: license-file
